<?xml version="1.0"?>
<odoo>
    <data>

        <record id="view_location_worker_form" model="ir.ui.view">
            <field name="name">stock.location.worker.form</field>
            <field name="model">stock.location</field>
            <field name="inherit_id" ref="stock.view_location_form"/>
            <field name="arch" type="xml">
                <field name="company_id" position="after">
                    <field name="warehouse_worker_id"/>
                </field>
            </field>
        </record>

    </data>
</odoo>
